fastapi_stats_page/__init__.py
fastapi_stats_page/stats.py
fastapi_stats_page/templates/stats.html
fastapi_stats_page-0.1.7.dist-info/METADATA
fastapi_stats_page-0.1.7.dist-info/WHEEL
fastapi_stats_page-0.1.7.dist-info/top_level.txt
fastapi_stats_page-0.1.7.dist-info/RECORD
