Metadata-Version: 2.4
Name: fastapi-stats-page
Version: 0.1.7
Summary: FastAPI visitor statistics with middleware and stats page
Author: Jackson Rodger
Classifier: Programming Language :: Python :: 3
Classifier: Framework :: FastAPI
Classifier: License :: OSI Approved :: MIT License
Classifier: Operating System :: OS Independent
Requires-Python: >=3.7
Requires-Dist: fastapi
Requires-Dist: jinja2
Requires-Dist: uvicorn
Dynamic: author
Dynamic: classifier
Dynamic: description
Dynamic: description-content-type
Dynamic: requires-dist
Dynamic: requires-python
Dynamic: summary
